web_2_album/__init__.py
web_2_album-0.0.74.dist-info/LICENSE
web_2_album-0.0.74.dist-info/METADATA
web_2_album-0.0.74.dist-info/WHEEL
web_2_album-0.0.74.dist-info/top_level.txt
web_2_album-0.0.74.dist-info/RECORD
