Metadata-Version: 2.1
Name: web-2-album
Version: 0.0.74
Summary: Return photo list and caption (markdown format) from web.
Home-page: https://github.com/gaoyunzhi/web_2_album
Author: Yunzhi Gao
Author-email: gaoyunzhi@gmail.com
License: UNKNOWN
Platform: UNKNOWN
Classifier: Programming Language :: Python :: 3
Classifier: License :: OSI Approved :: MIT License
Classifier: Operating System :: OS Independent
Requires-Python: >=3.0
License-File: LICENSE
Requires-Dist: cached-url
Requires-Dist: bs4
Requires-Dist: telegram-util
Requires-Dist: export-to-telegraph
Requires-Dist: readee
Requires-Dist: pyyaml
